wmul_emailer/__init__.py
wmul_emailer/cli.py
wmul_emailer-0.6.0.dist-info/entry_points.txt
wmul_emailer-0.6.0.dist-info/LICENSE
wmul_emailer-0.6.0.dist-info/WHEEL
wmul_emailer-0.6.0.dist-info/METADATA
wmul_emailer-0.6.0.dist-info/RECORD
