Metadata-Version: 2.1
Name: wmul_emailer
Version: 0.6.0
Summary: Utility to send an email to multiple addresses.
Author-email: Michael Stanley <stanley50@marshall.edu>
Requires-Python: >=3.6
Classifier: Programming Language :: Python :: 3
Classifier: License :: OSI Approved :: GNU General Public License v3 or later (GPLv3+)
Classifier: Operating System :: OS Independent
Classifier: Development Status :: 5 - Production/Stable
Classifier: Topic :: Communications :: Email
Requires-Dist: click
Requires-Dist: wmul_click_utils
Requires-Dist: pytest ; extra == "test"
Requires-Dist: pytest-mock ; extra == "test"
Requires-Dist: wmul_test_utils ; extra == "test"
Requires-Dist: tox ; extra == "tox"
Project-URL: Bug Tracker, https://github.com/MikeTheHammer/wmul_emailer/issues
Project-URL: Homepage, https://github.com/MikeTheHammer/wmul_emailer
Provides-Extra: test
Provides-Extra: tox
